setup.py
meteorpi_server/__init__.py
meteorpi_server/admin_api.py
meteorpi_server/importer_api.py
meteorpi_server/query_api.py
meteorpi_server/run_test_1.py
meteorpi_server/run_test_2.py
meteorpi_server.egg-info/PKG-INFO
meteorpi_server.egg-info/SOURCES.txt
meteorpi_server.egg-info/dependency_links.txt
meteorpi_server.egg-info/not-zip-safe
meteorpi_server.egg-info/requires.txt
meteorpi_server.egg-info/top_level.txt