Metadata-Version: 1.1
Name: meteorpi-server
Version: 0.1.5
Summary: HTTP server based on Flask providing a remote API
Home-page: https://github.com/camsci/meteor-pi/
Author: Tom Oinn
Author-email: tomoinn@crypticsquid.com
License: GPL
Platform: UNKNOWN
Classifier: Programming Language :: Python :: 2.7
